{"stats":{"minecraft:mined":{"ancientgateways:rune_magenta":1,"ancientgateways:rune_lime":1,"ancientgateways:rune_blue":1,"ancientgateways:rune_yellow":1,"ancientgateways:rune_red":1,"ancientgateways:gatewayblock":4,"ancientgateways:rune_white":1,"ancientgateways:rune_green":1,"ancientgateways:rune_pink":1,"ancientgateways:rune_orange":1,"ancientgateways:rune_purple":1,"ancientgateways:rune_black":1,"ancientgateways:rune_grey":1,"ancientgateways:rune_light_grey":1,"ancientgateways:rune_cyan":1,"ancientgateways:rune_light_blue":1,"ancientgateways:rune_brown":1},"minecraft:picked_up":{"ancientgateways:rune_black":1,"ancientgateways:rune_red":1,"ancientgateways:rune_pink":1,"ancientgateways:rune_purple":1,"ancientgateways:rune_grey":1,"ancientgateways:rune_white":1,"ancientgateways:gatewayblock":4,"ancientgateways:rune_brown":1,"ancientgateways:rune_green":1,"ancientgateways:rune_cyan":1,"ancientgateways:rune_lime":1,"ancientgateways:rune_magenta":1,"ancientgateways:rune_light_blue":1,"ancientgateways:rune_light_grey":1,"ancientgateways:rune_blue":1,"ancientgateways:rune_orange":1,"ancientgateways:rune_yellow":1},"minecraft:custom":{"minecraft:time_since_rest":16217,"minecraft:sprint_one_cm":27292,"minecraft:walk_one_cm":30536,"minecraft:fly_one_cm":30713,"minecraft:crouch_one_cm":1108,"minecraft:play_one_minute":16217,"minecraft:sneak_time":337,"minecraft:jump":56,"minecraft:leave_game":3,"minecraft:time_since_death":16217},"minecraft:used":{"ancientgateways:rune_cyan":1,"ancientgateways:rune_light_grey":1,"minecraft:diamond_pickaxe":3,"ancientgateways:rune_orange":1,"ancientgateways:rune_blue":1,"ancientgateways:rune_black":1,"ancientgateways:rune_lime":1,"ancientgateways:gatewayblock":4,"ancientgateways:rune_red":1,"ancientgateways:rune_yellow":1,"ancientgateways:rune_magenta":1,"ancientgateways:rune_light_blue":1,"ancientgateways:rune_grey":1,"ancientgateways:rune_pink":1,"ancientgateways:rune_green":1,"ancientgateways:rune_brown":1,"minecraft:white_concrete":22,"ancientgateways:rune_white":2,"ancientgateways:rune_purple":1}},"DataVersion":2580}